{
    "ETag": "E2EUQ1WTGCTBG2",
    "Distribution": {
        "Id": "E2OLRP16M134FM",
        "ARN": "arn:aws:cloudfront::044260498664:distribution/E2OLRP16M134FM",
        "Status": "Deployed",
        "LastModifiedTime": "2026-03-04T02:42:04.344000+00:00",
        "InProgressInvalidationBatches": 0,
        "DomainName": "dr0w8c035kcym.cloudfront.net",
        "ActiveTrustedSigners": {
            "Enabled": false,
            "Quantity": 0
        },
        "ActiveTrustedKeyGroups": {
            "Enabled": false,
            "Quantity": 0
        },
        "DistributionConfig": {
            "CallerReference": "nextdeploy-nextdeploy-nextdeploy-frontend-production-assets-044260498664",
            "Aliases": {
                "Quantity": 0
            },
            "DefaultRootObject": "",
            "Origins": {
                "Quantity": 2,
                "Items": [
                    {
                        "Id": "LambdaCompute",
                        "DomainName": "vyv3cranh2cxir75h3xdpl3sdy0uxjmh.lambda-url.us-east-1.on.aws",
                        "OriginPath": "",
                        "CustomHeaders": {
                            "Quantity": 0
                        },
                        "CustomOriginConfig": {
                            "HTTPPort": 80,
                            "HTTPSPort": 443,
                            "OriginProtocolPolicy": "https-only",
                            "OriginSslProtocols": {
                                "Quantity": 1,
                                "Items": [
                                    "TLSv1.2"
                                ]
                            },
                            "OriginReadTimeout": 30,
                            "OriginKeepaliveTimeout": 5
                        },
                        "ConnectionAttempts": 3,
                        "ConnectionTimeout": 10,
                        "OriginShield": {
                            "Enabled": false
                        },
                        "OriginAccessControlId": "E26PXA2H3PUCV9"
                    },
                    {
                        "Id": "S3Assets",
                        "DomainName": "nextdeploy-nextdeploy-frontend-production-assets-044260498664.s3.us-east-1.amazonaws.com",
                        "OriginPath": "",
                        "CustomHeaders": {
                            "Quantity": 0
                        },
                        "S3OriginConfig": {
                            "OriginAccessIdentity": "",
                            "OriginReadTimeout": 30
                        },
                        "ConnectionAttempts": 3,
                        "ConnectionTimeout": 10,
                        "OriginShield": {
                            "Enabled": false
                        },
                        "OriginAccessControlId": "E1P3ROGX57P0"
                    }
                ]
            },
            "OriginGroups": {
                "Quantity": 0
            },
            "DefaultCacheBehavior": {
                "TargetOriginId": "LambdaCompute",
                "TrustedSigners": {
                    "Enabled": false,
                    "Quantity": 0
                },
                "TrustedKeyGroups": {
                    "Enabled": false,
                    "Quantity": 0
                },
                "ViewerProtocolPolicy": "redirect-to-https",
                "AllowedMethods": {
                    "Quantity": 7,
                    "Items": [
                        "HEAD",
                        "DELETE",
                        "POST",
                        "GET",
                        "OPTIONS",
                        "PUT",
                        "PATCH"
                    ],
                    "CachedMethods": {
                        "Quantity": 2,
                        "Items": [
                            "HEAD",
                            "GET"
                        ]
                    }
                },
                "SmoothStreaming": false,
                "Compress": false,
                "LambdaFunctionAssociations": {
                    "Quantity": 0
                },
                "FunctionAssociations": {
                    "Quantity": 0
                },
                "FieldLevelEncryptionId": "",
                "CachePolicyId": "4135ea2d-6df8-44a3-9df3-4b5a84be39ad",
                "OriginRequestPolicyId": "b689b0a8-53d0-40ab-baf2-68738e2966ac",
                "GrpcConfig": {
                    "Enabled": false
                }
            },
            "CacheBehaviors": {
                "Quantity": 2,
                "Items": [
                    {
                        "PathPattern": "/_next/*",
                        "TargetOriginId": "S3Assets",
                        "TrustedSigners": {
                            "Enabled": false,
                            "Quantity": 0
                        },
                        "TrustedKeyGroups": {
                            "Enabled": false,
                            "Quantity": 0
                        },
                        "ViewerProtocolPolicy": "redirect-to-https",
                        "AllowedMethods": {
                            "Quantity": 2,
                            "Items": [
                                "HEAD",
                                "GET"
                            ],
                            "CachedMethods": {
                                "Quantity": 2,
                                "Items": [
                                    "HEAD",
                                    "GET"
                                ]
                            }
                        },
                        "SmoothStreaming": false,
                        "Compress": false,
                        "LambdaFunctionAssociations": {
                            "Quantity": 0
                        },
                        "FunctionAssociations": {
                            "Quantity": 0
                        },
                        "FieldLevelEncryptionId": "",
                        "CachePolicyId": "658327ea-f89d-4fab-a63d-7e88639e58f6",
                        "GrpcConfig": {
                            "Enabled": false
                        }
                    },
                    {
                        "PathPattern": "/assets/*",
                        "TargetOriginId": "S3Assets",
                        "TrustedSigners": {
                            "Enabled": false,
                            "Quantity": 0
                        },
                        "TrustedKeyGroups": {
                            "Enabled": false,
                            "Quantity": 0
                        },
                        "ViewerProtocolPolicy": "redirect-to-https",
                        "AllowedMethods": {
                            "Quantity": 2,
                            "Items": [
                                "HEAD",
                                "GET"
                            ],
                            "CachedMethods": {
                                "Quantity": 2,
                                "Items": [
                                    "HEAD",
                                    "GET"
                                ]
                            }
                        },
                        "SmoothStreaming": false,
                        "Compress": false,
                        "LambdaFunctionAssociations": {
                            "Quantity": 0
                        },
                        "FunctionAssociations": {
                            "Quantity": 0
                        },
                        "FieldLevelEncryptionId": "",
                        "CachePolicyId": "658327ea-f89d-4fab-a63d-7e88639e58f6",
                        "GrpcConfig": {
                            "Enabled": false
                        }
                    }
                ]
            },
            "CustomErrorResponses": {
                "Quantity": 0
            },
            "Comment": "nextdeploy-nextdeploy-nextdeploy-frontend-production-assets-044260498664",
            "Logging": {
                "Enabled": false,
                "IncludeCookies": false,
                "Bucket": "",
                "Prefix": ""
            },
            "PriceClass": "PriceClass_All",
            "Enabled": true,
            "ViewerCertificate": {
                "CloudFrontDefaultCertificate": true,
                "SSLSupportMethod": "vip",
                "MinimumProtocolVersion": "TLSv1",
                "CertificateSource": "cloudfront"
            },
            "Restrictions": {
                "GeoRestriction": {
                    "RestrictionType": "none",
                    "Quantity": 0
                }
            },
            "WebACLId": "",
            "HttpVersion": "http2",
            "IsIPV6Enabled": true,
            "ContinuousDeploymentPolicyId": "",
            "Staging": false
        }
    }
}
